{"stats":{"minecraft:dropped":{"minecraft:sand":1},"minecraft:custom":{"minecraft:time_since_rest":9044,"minecraft:open_chest":4,"minecraft:play_time":9044,"minecraft:sprint_one_cm":1424,"minecraft:damage_taken":10,"minecraft:walk_one_cm":25234,"minecraft:drop":1,"minecraft:jump":70,"minecraft:damage_dealt":6,"minecraft:leave_game":4,"minecraft:time_since_death":9044,"minecraft:total_world_time":9044,"minecraft:interact_with_crafting_table":2,"minecraft:fall_one_cm":1370,"minecraft:fly_one_cm":622},"minecraft:used":{"minecraft:stone_sword":3,"minecraft:sand":1,"minecraft:diamond_helmet":1},"minecraft:picked_up":{"minecraft:sand":4,"minecraft:sugar_cane":9,"minecraft:dirt":3},"minecraft:crafted":{"minecraft:sugar":5},"minecraft:mined":{"minecraft:grass_block":3,"minecraft:sand":4,"minecraft:sugar_cane":7}},"DataVersion":3337}